CHANGES.txt
README.txt
bootstrap.py
buildout.cfg
setup.py
src/z3c/__init__.py
src/z3c.feature.core.egg-info/PKG-INFO
src/z3c.feature.core.egg-info/SOURCES.txt
src/z3c.feature.core.egg-info/dependency_links.txt
src/z3c.feature.core.egg-info/entry_points.txt
src/z3c.feature.core.egg-info/namespace_packages.txt
src/z3c.feature.core.egg-info/not-zip-safe
src/z3c.feature.core.egg-info/requires.txt
src/z3c.feature.core.egg-info/top_level.txt
src/z3c/feature/__init__.py
src/z3c/feature/core/README.txt
src/z3c/feature/core/__init__.py
src/z3c/feature/core/base.py
src/z3c/feature/core/base.txt
src/z3c/feature/core/command-line-project.xml
src/z3c/feature/core/example.txt
src/z3c/feature/core/index.txt
src/z3c/feature/core/interfaces.py
src/z3c/feature/core/metadata.py
src/z3c/feature/core/metadata.txt
src/z3c/feature/core/python-package-project.xml
src/z3c/feature/core/python.py
src/z3c/feature/core/python.txt
src/z3c/feature/core/template.py
src/z3c/feature/core/testing.py
src/z3c/feature/core/unittest.py
src/z3c/feature/core/unittest.txt
src/z3c/feature/core/xml.py
src/z3c/feature/core/xml.txt
src/z3c/feature/core/file-templates/README.txt
src/z3c/feature/core/file-templates/index-template.txt
src/z3c/feature/core/file-templates/test_doc.py
src/z3c/feature/core/tests/__init__.py
src/z3c/feature/core/tests/test_doc.py
src/z3c/feature/core/web/__init__.py
src/z3c/feature/core/web/metadata.py
src/z3c/feature/core/web/python.py
src/z3c/feature/core/web/unittest.py
src/z3c/feature/core/web/templates/comment-header-zpl.pt
src/z3c/feature/core/web/templates/metadata.js
src/z3c/feature/core/web/templates/metadata.pt
src/z3c/feature/core/web/templates/proprietary-header.pt