Metadata-Version: 1.0
Name: z3c.feature.core
Version: 0.1.1
Summary: Core Features to use with z3c.builder.core
Home-page: http://pypi.python.org/pypi/z3c.feature.core
Author: Paul Carduner and Stephan Richter
Author-email: zope-dev@zope.org
License: ZPL
Keywords: z,o,p,e,3, ,p,r,o,j,e,c,t, ,b,u,i,l,d,e,r, ,f,e,a,t,u,r,e
Platform: UNKNOWN
